CHANGELOG.rst
LICENSE.txt
MANIFEST.in
README.rst
VERSION.txt
setup.cfg
setup.py
csvsed/__init__.py
csvsed/cli.py
csvsed/sed.py
csvsed/test.py
csvsed.egg-info/PKG-INFO
csvsed.egg-info/SOURCES.txt
csvsed.egg-info/dependency_links.txt
csvsed.egg-info/entry_points.txt
csvsed.egg-info/requires.txt
csvsed.egg-info/top_level.txt
csvsed.egg-info/zip-safe