Metadata-Version: 1.1
Name: csvsed
Version: 0.2.4
Summary: A stream-oriented CSV modification tool
Home-page: http://github.com/metagriffin/csvsed
Author: metagriffin
Author-email: metagriffin@uberdev.org
License: GPLv3+
Keywords: CSV comma separated values modification substitution translation transliteration command-line library
Platform: any
Classifier: Development Status :: 4 - Beta
Classifier: Environment :: Console
Classifier: Intended Audience :: Developers
Classifier: Intended Audience :: System Administrators
Classifier: Natural Language :: English
Classifier: Operating System :: OS Independent
Classifier: Programming Language :: Python
Classifier: Topic :: Software Development
Classifier: Topic :: Software Development :: Libraries :: Python Modules
Classifier: Topic :: Utilities
Classifier: License :: OSI Approved :: GNU General Public License v3 or later (GPLv3+)
